{
    "token":"********",
    "team_id":"*****",
    "api_app_id":"****",
    "event":{
       "client_msg_id":"**",
       "type":"message",
       "text":"help waf",
       "user":"**",
       "ts":"**",
       "team":"**",
       "blocks":[
          {
             "type":"rich_text",
             "block_id":"rIN",
             "elements":[
                {
                   "type":"rich_text_section",
                   "elements":[
                      {
                         "type":"text",
                         "text":"help waf"
                      }
                   ]
                }
             ]
          }
       ],
       "channel":"****",
       "event_ts":"1******",
       "channel_type":"im"
    },
    "type":"event_callback",
    "event_id":"****",
    "event_time":1234,
    "authed_users":[
       "******"
    ]
 }